{
  "B084KW7N8C": {
    "nombre": "Flexispot E7 Escritorio Elevable Electrico",
    "marca": "Flexispot",
    "modelo": "E7",
    "precio": 480,
    "precio_habitual": 530,
    "imagen": "https://m.media-amazon.com/images/I/71--Rk-6uiL._AC_SL1500_.jpg",
    "imagen_alt": "Flexispot E7 escritorio elevable electrico doble motor",
    "rating": 4.6,
    "num_reviews": 3200,
    "disponible": true,
    "specs": {
      "tipo_motor": "doble",
      "rango_altura_min_cm": 58,
      "rango_altura_max_cm": 123,
      "velocidad_cm_s": 3.8,
      "peso_max_carga_kg": 125,
      "ancho_tablero_cm": 140,
      "profundidad_tablero_cm": 70,
      "peso_estructura_kg": 32.1,
      "ruido_db": 45,
      "presets_memoria": 4,
      "sistema_anticolision": true,
      "tablero_incluido": true,
      "material_tablero": "melamina",
      "garantia_anos": 5
    },
    "categorias": ["premium", "oficina", "recomendado"],
    "pros": [
      "Motor doble muy estable a cualquier altura",
      "Rango de 58-123 cm cubre casi cualquier estatura",
      "125 kg de carga: soporta setup completo",
      "4 presets de memoria",
      "5 anos de garantia"
    ],
    "contras": [
      "Precio por encima de 450 EUR",
      "Montaje requiere dos personas"
    ],
    "veredicto": "El mejor escritorio elevable para quien busca calidad y estabilidad sin compromisos.",
    "puntuacion": {
      "calidad_construccion": 9,
      "estabilidad": 9,
      "facilidad_montaje": 7,
      "relacion_calidad_precio": 8,
      "funcionalidades": 8,
      "total": 8.4
    },
    "ideal_para": "Profesionales en teletrabajo que quieren un escritorio para anos.",
    "slug": "flexispot-e7"
  },
  "B087JF3B5S": {
    "nombre": "Maidesite T2 Pro Plus Escritorio Elevable",
    "marca": "Maidesite",
    "modelo": "T2 Pro Plus",
    "precio": 270,
    "precio_habitual": 320,
    "imagen": "https://m.media-amazon.com/images/I/71JCvElrIhL._AC_SL1500_.jpg",
    "imagen_alt": "Maidesite T2 Pro Plus escritorio elevable electrico",
    "rating": 4.4,
    "num_reviews": 1850,
    "disponible": true,
    "specs": {
      "tipo_motor": "doble",
      "rango_altura_min_cm": 62,
      "rango_altura_max_cm": 127,
      "velocidad_cm_s": 3.8,
      "peso_max_carga_kg": 100,
      "ancho_tablero_cm": 140,
      "profundidad_tablero_cm": 70,
      "peso_estructura_kg": 27,
      "ruido_db": 48,
      "presets_memoria": 4,
      "sistema_anticolision": true,
      "tablero_incluido": true,
      "material_tablero": "melamina",
      "garantia_anos": 5
    },
    "categorias": ["calidad-precio", "oficina"],
    "pros": [
      "Mejor relacion calidad-precio del mercado",
      "Doble motor a precio de motor simple",
      "127 cm de altura maxima",
      "4 presets de memoria"
    ],
    "contras": [
      "Algo menos estable que el E7 a maxima altura",
      "Tablero algo fino"
    ],
    "veredicto": "La mejor opcion calidad-precio. Doble motor por menos de 300 EUR.",
    "puntuacion": {
      "calidad_construccion": 7,
      "estabilidad": 7,
      "facilidad_montaje": 8,
      "relacion_calidad_precio": 10,
      "funcionalidades": 8,
      "total": 8.0
    },
    "ideal_para": "Quien busca doble motor sin gastar mas de 300 EUR.",
    "slug": "maidesite-t2-pro"
  },
  "B0DZHHK3L3": {
    "nombre": "SANODESK QS+ Escritorio Elevable",
    "marca": "SANODESK",
    "modelo": "QS+",
    "precio": 190,
    "precio_habitual": null,
    "imagen": "https://m.media-amazon.com/images/I/61Uz3lB4v9L._AC_SL1500_.jpg",
    "imagen_alt": "SANODESK QS+ escritorio elevable electrico barato",
    "rating": 4.3,
    "num_reviews": 980,
    "disponible": true,
    "specs": {
      "tipo_motor": "simple",
      "rango_altura_min_cm": 72,
      "rango_altura_max_cm": 120,
      "velocidad_cm_s": 2.5,
      "peso_max_carga_kg": 70,
      "ancho_tablero_cm": 120,
      "profundidad_tablero_cm": 60,
      "peso_estructura_kg": 20,
      "ruido_db": 50,
      "presets_memoria": 3,
      "sistema_anticolision": false,
      "tablero_incluido": true,
      "material_tablero": "melamina",
      "garantia_anos": 3
    },
    "categorias": ["barato"],
    "pros": [
      "Precio imbatible por debajo de 200 EUR",
      "Facil de montar en 30 minutos",
      "3 memorias de altura"
    ],
    "contras": [
      "Motor simple: mas lento y menos peso",
      "Sin sistema anticolision",
      "Rango de altura limitado (72-120 cm)"
    ],
    "veredicto": "El escritorio elevable mas barato que merece la pena. Ideal para empezar.",
    "puntuacion": {
      "calidad_construccion": 6,
      "estabilidad": 6,
      "facilidad_montaje": 9,
      "relacion_calidad_precio": 9,
      "funcionalidades": 5,
      "total": 7.0
    },
    "ideal_para": "Presupuesto ajustado o primer escritorio elevable.",
    "slug": "sanodesk-qs-plus"
  },
  "B09DCNDGWB": {
    "nombre": "Flexispot E7 Pro Escritorio Elevable",
    "marca": "Flexispot",
    "modelo": "E7 Pro",
    "precio": 550,
    "precio_habitual": 600,
    "imagen": "https://m.media-amazon.com/images/I/61ONgqMe-DL._AC_SL1500_.jpg",
    "imagen_alt": "Flexispot E7 Pro escritorio elevable premium doble motor",
    "rating": 4.7,
    "num_reviews": 1200,
    "disponible": true,
    "specs": {
      "tipo_motor": "doble",
      "rango_altura_min_cm": 60,
      "rango_altura_max_cm": 125,
      "velocidad_cm_s": 4.0,
      "peso_max_carga_kg": 150,
      "ancho_tablero_cm": 160,
      "profundidad_tablero_cm": 80,
      "peso_estructura_kg": 35,
      "ruido_db": 43,
      "presets_memoria": 4,
      "sistema_anticolision": true,
      "tablero_incluido": true,
      "material_tablero": "bambu",
      "garantia_anos": 5
    },
    "categorias": ["premium", "oficina"],
    "pros": [
      "150 kg de carga: el mas robusto del mercado",
      "Motor mas rapido (4 cm/s) y silencioso (43 dB)",
      "Tablero de bambu de alta calidad",
      "Estructura de acero reforzada"
    ],
    "contras": [
      "Precio elevado: mas de 500 EUR",
      "Peso de la estructura (35 kg): necesitas ayuda para montar",
      "Overkill si tu setup es sencillo"
    ],
    "veredicto": "El tope de gama de Flexispot. Para quien quiere lo mejor sin mirar el precio.",
    "puntuacion": {
      "calidad_construccion": 10,
      "estabilidad": 10,
      "facilidad_montaje": 6,
      "relacion_calidad_precio": 7,
      "funcionalidades": 9,
      "total": 8.6
    },
    "ideal_para": "Setup pesado con multiples monitores o uso profesional intensivo.",
    "slug": "flexispot-e7-pro"
  },
  "B0BSL741RM": {
    "nombre": "JUMMICO Escritorio Elevable Electrico",
    "marca": "JUMMICO",
    "modelo": "HED-12",
    "precio": 160,
    "precio_habitual": 200,
    "imagen": "https://m.media-amazon.com/images/I/61u1kdqoDoL._AC_SL1500_.jpg",
    "imagen_alt": "JUMMICO HED-12 escritorio elevable electrico economico",
    "rating": 4.2,
    "num_reviews": 650,
    "disponible": true,
    "specs": {
      "tipo_motor": "simple",
      "rango_altura_min_cm": 73,
      "rango_altura_max_cm": 118,
      "velocidad_cm_s": 2.5,
      "peso_max_carga_kg": 60,
      "ancho_tablero_cm": 100,
      "profundidad_tablero_cm": 60,
      "peso_estructura_kg": 18,
      "ruido_db": 52,
      "presets_memoria": 3,
      "sistema_anticolision": false,
      "tablero_incluido": true,
      "material_tablero": "melamina",
      "garantia_anos": 2
    },
    "categorias": ["barato"],
    "pros": [
      "El mas barato del mercado",
      "Compacto: cabe en espacios pequenos",
      "Montaje muy sencillo"
    ],
    "contras": [
      "Solo 60 kg de carga",
      "Motor lento y algo ruidoso",
      "Tablero de 100 cm: pequeno para dual monitor",
      "Solo 2 anos de garantia"
    ],
    "veredicto": "Para espacios pequenos y presupuestos minimos. No esperes milagros.",
    "puntuacion": {
      "calidad_construccion": 5,
      "estabilidad": 5,
      "facilidad_montaje": 9,
      "relacion_calidad_precio": 8,
      "funcionalidades": 4,
      "total": 6.2
    },
    "ideal_para": "Estudiantes o espacios pequenos con presupuesto minimo.",
    "slug": "jummico-hed12"
  },
  "B09GLNM2GS": {
    "nombre": "Flexispot EG8 Escritorio Elevable Gaming",
    "marca": "Flexispot",
    "modelo": "EG8",
    "precio": 500,
    "precio_habitual": null,
    "imagen": "https://m.media-amazon.com/images/I/61b4lh-o-+L._AC_SL1500_.jpg",
    "imagen_alt": "Flexispot EG8 escritorio elevable gaming con cajon",
    "rating": 4.5,
    "num_reviews": 780,
    "disponible": true,
    "specs": {
      "tipo_motor": "doble",
      "rango_altura_min_cm": 61,
      "rango_altura_max_cm": 124,
      "velocidad_cm_s": 3.8,
      "peso_max_carga_kg": 125,
      "ancho_tablero_cm": 155,
      "profundidad_tablero_cm": 70,
      "peso_estructura_kg": 33,
      "ruido_db": 45,
      "presets_memoria": 4,
      "sistema_anticolision": true,
      "tablero_incluido": true,
      "material_tablero": "fibra de carbono",
      "garantia_anos": 5
    },
    "categorias": ["gaming", "premium"],
    "pros": [
      "Diseno gaming con cajon integrado y USB",
      "Tablero de fibra de carbono resistente",
      "Mismo motor que el E7: fiable",
      "Gestion de cables integrada"
    ],
    "contras": [
      "Precio similar al E7 pero con acabado gaming",
      "Menos profesional para videollamadas",
      "Solo disponible en negro"
    ],
    "veredicto": "El E7 con traje de gaming. Si te va la estetica gamer, es la opcion.",
    "puntuacion": {
      "calidad_construccion": 8,
      "estabilidad": 9,
      "facilidad_montaje": 7,
      "relacion_calidad_precio": 7,
      "funcionalidades": 8,
      "total": 7.8
    },
    "ideal_para": "Gamers que quieren un escritorio elevable sin renunciar a la estetica.",
    "slug": "flexispot-eg8"
  },
  "B0CJ3KRQBY": {
    "nombre": "Fezibo Escritorio Elevable Electrico 100x60",
    "marca": "Fezibo",
    "modelo": "100x60",
    "precio": 120,
    "precio_habitual": 150,
    "imagen": "https://m.media-amazon.com/images/I/71E-eMT7vBL._AC_SL1500_.jpg",
    "imagen_alt": "Fezibo escritorio elevable electrico barato 100x60",
    "rating": 4.3,
    "num_reviews": 2400,
    "disponible": true,
    "specs": {
      "tipo_motor": "simple",
      "rango_altura_min_cm": 72,
      "rango_altura_max_cm": 116,
      "velocidad_cm_s": 2.5,
      "peso_max_carga_kg": 50,
      "ancho_tablero_cm": 100,
      "profundidad_tablero_cm": 60,
      "peso_estructura_kg": 16,
      "ruido_db": 50,
      "presets_memoria": 3,
      "sistema_anticolision": false,
      "tablero_incluido": true,
      "material_tablero": "melamina",
      "garantia_anos": 2
    },
    "categorias": ["barato", "compacto"],
    "pros": [
      "Uno de los mas baratos del mercado por 120 EUR",
      "Mas de 2400 opiniones en Amazon con buena nota",
      "Bandeja para teclado incluida",
      "Montaje rapido en 20 minutos"
    ],
    "contras": [
      "Solo 50 kg de carga: para setup ligero",
      "Tablero pequeno (100x60 cm)",
      "Motor lento y sin anticolision",
      "Garantia corta: 2 anos"
    ],
    "veredicto": "El mejor escritorio elevable por debajo de 130 EUR. Ideal para empezar sin gastar mucho.",
    "puntuacion": {
      "calidad_construccion": 5,
      "estabilidad": 5,
      "facilidad_montaje": 9,
      "relacion_calidad_precio": 9,
      "funcionalidades": 5,
      "total": 6.6
    },
    "ideal_para": "Primer escritorio elevable con presupuesto minimo.",
    "slug": "fezibo-100x60"
  },
  "B0D5W2M8H7": {
    "nombre": "Ergear Escritorio Elevable Electrico 120x60",
    "marca": "Ergear",
    "modelo": "EED-S1",
    "precio": 140,
    "precio_habitual": 170,
    "imagen": "https://m.media-amazon.com/images/I/71uRYLyz-YL._AC_SL1500_.jpg",
    "imagen_alt": "Ergear escritorio elevable electrico 120x60 barato",
    "rating": 4.4,
    "num_reviews": 1800,
    "disponible": true,
    "specs": {
      "tipo_motor": "simple",
      "rango_altura_min_cm": 72,
      "rango_altura_max_cm": 120,
      "velocidad_cm_s": 2.5,
      "peso_max_carga_kg": 70,
      "ancho_tablero_cm": 120,
      "profundidad_tablero_cm": 60,
      "peso_estructura_kg": 19,
      "ruido_db": 48,
      "presets_memoria": 4,
      "sistema_anticolision": true,
      "tablero_incluido": true,
      "material_tablero": "melamina",
      "garantia_anos": 3
    },
    "categorias": ["barato", "calidad-precio"],
    "pros": [
      "Anticolision por debajo de 150 EUR",
      "4 memorias: mas que otros baratos",
      "Tablero 120 cm: cabe monitor + portatil",
      "1800+ opiniones con 4.4 estrellas"
    ],
    "contras": [
      "Motor simple: algo lento (2.5 cm/s)",
      "Estabilidad mejorable a maxima altura",
      "Tablero basico de melamina"
    ],
    "veredicto": "La mejor opcion barata con anticolision. Tablero de 120 cm por menos de 150 EUR.",
    "puntuacion": {
      "calidad_construccion": 6,
      "estabilidad": 6,
      "facilidad_montaje": 8,
      "relacion_calidad_precio": 9,
      "funcionalidades": 7,
      "total": 7.2
    },
    "ideal_para": "Quien quiere un escritorio barato pero con funciones de uno caro.",
    "slug": "ergear-eed-s1"
  },
  "B0C8N3VPT5": {
    "nombre": "BANTI Escritorio Elevable Electrico 110x60",
    "marca": "BANTI",
    "modelo": "EU-B-SED-10",
    "precio": 110,
    "precio_habitual": 140,
    "imagen": "https://m.media-amazon.com/images/I/71gGjmKLURL._AC_SL1500_.jpg",
    "imagen_alt": "BANTI escritorio elevable electrico ultra barato",
    "rating": 4.1,
    "num_reviews": 920,
    "disponible": true,
    "specs": {
      "tipo_motor": "simple",
      "rango_altura_min_cm": 73,
      "rango_altura_max_cm": 114,
      "velocidad_cm_s": 2.3,
      "peso_max_carga_kg": 50,
      "ancho_tablero_cm": 110,
      "profundidad_tablero_cm": 60,
      "peso_estructura_kg": 17,
      "ruido_db": 52,
      "presets_memoria": 3,
      "sistema_anticolision": false,
      "tablero_incluido": true,
      "material_tablero": "melamina",
      "garantia_anos": 2
    },
    "categorias": ["barato"],
    "pros": [
      "El escritorio elevable mas barato: 110 EUR",
      "Tablero de 110 cm: algo mas amplio que el Fezibo",
      "Montaje sencillo con instrucciones claras"
    ],
    "contras": [
      "Solo 50 kg de carga",
      "Rango de altura limitado (73-114 cm)",
      "Motor el mas lento del mercado (2.3 cm/s)",
      "Sin anticolision ni funciones extra"
    ],
    "veredicto": "El precio mas bajo del mercado. Si buscas lo mas barato posible, es tu opcion.",
    "puntuacion": {
      "calidad_construccion": 4,
      "estabilidad": 5,
      "facilidad_montaje": 9,
      "relacion_calidad_precio": 8,
      "funcionalidades": 3,
      "total": 5.8
    },
    "ideal_para": "Presupuesto ultra ajustado. El minimo para tener un escritorio que sube y baja.",
    "slug": "banti-110x60"
  },
  "B0CQZ8N7VL": {
    "nombre": "Flexispot EG1 Escritorio Elevable",
    "marca": "Flexispot",
    "modelo": "EG1",
    "precio": 210,
    "precio_habitual": 250,
    "imagen": "https://m.media-amazon.com/images/I/61C7ZHkr-KL._AC_SL1500_.jpg",
    "imagen_alt": "Flexispot EG1 escritorio elevable electrico entrada",
    "rating": 4.5,
    "num_reviews": 1500,
    "disponible": true,
    "specs": {
      "tipo_motor": "simple",
      "rango_altura_min_cm": 72,
      "rango_altura_max_cm": 121,
      "velocidad_cm_s": 2.5,
      "peso_max_carga_kg": 70,
      "ancho_tablero_cm": 120,
      "profundidad_tablero_cm": 60,
      "peso_estructura_kg": 21,
      "ruido_db": 48,
      "presets_memoria": 3,
      "sistema_anticolision": true,
      "tablero_incluido": true,
      "material_tablero": "melamina",
      "garantia_anos": 5
    },
    "categorias": ["calidad-precio", "oficina"],
    "pros": [
      "Marca Flexispot por poco mas de 200 EUR",
      "5 anos de garantia: la mejor en su rango",
      "Anticolision incluido",
      "1500+ opiniones con 4.5 estrellas"
    ],
    "contras": [
      "Motor simple: mas lento que los doble motor",
      "Tablero de 120x60: justo para dual monitor",
      "Sin USB ni extras"
    ],
    "veredicto": "La puerta de entrada a Flexispot. Calidad de marca por precio de generico.",
    "puntuacion": {
      "calidad_construccion": 7,
      "estabilidad": 7,
      "facilidad_montaje": 8,
      "relacion_calidad_precio": 9,
      "funcionalidades": 6,
      "total": 7.4
    },
    "ideal_para": "Quien quiere calidad Flexispot sin llegar a los 300 EUR.",
    "slug": "flexispot-eg1"
  },
  "B0CFXKQWZR": {
    "nombre": "Maidesite S2 Pro Escritorio Elevable",
    "marca": "Maidesite",
    "modelo": "S2 Pro",
    "precio": 200,
    "precio_habitual": 240,
    "imagen": "https://m.media-amazon.com/images/I/71oFpYY5O9L._AC_SL1500_.jpg",
    "imagen_alt": "Maidesite S2 Pro escritorio elevable electrico gama media",
    "rating": 4.3,
    "num_reviews": 1100,
    "disponible": true,
    "specs": {
      "tipo_motor": "simple",
      "rango_altura_min_cm": 72,
      "rango_altura_max_cm": 120,
      "velocidad_cm_s": 2.5,
      "peso_max_carga_kg": 80,
      "ancho_tablero_cm": 120,
      "profundidad_tablero_cm": 60,
      "peso_estructura_kg": 22,
      "ruido_db": 48,
      "presets_memoria": 4,
      "sistema_anticolision": true,
      "tablero_incluido": true,
      "material_tablero": "melamina",
      "garantia_anos": 5
    },
    "categorias": ["calidad-precio", "oficina"],
    "pros": [
      "80 kg de carga: el mejor de su rango de precio",
      "4 memorias + anticolision por 200 EUR",
      "5 anos de garantia",
      "Marca de confianza con buen soporte"
    ],
    "contras": [
      "Motor simple",
      "Tablero basico de melamina",
      "Menos opiniones que la competencia"
    ],
    "veredicto": "El Maidesite economico. Buenas prestaciones por 200 EUR con garantia larga.",
    "puntuacion": {
      "calidad_construccion": 7,
      "estabilidad": 7,
      "facilidad_montaje": 8,
      "relacion_calidad_precio": 9,
      "funcionalidades": 7,
      "total": 7.6
    },
    "ideal_para": "Quien quiere la fiabilidad Maidesite sin pagar precio premium.",
    "slug": "maidesite-s2-pro"
  },
  "B0D8K2MLQT": {
    "nombre": "VASAGLE Escritorio Elevable Electrico 140x70",
    "marca": "VASAGLE",
    "modelo": "LSD302",
    "precio": 180,
    "precio_habitual": 220,
    "imagen": "https://m.media-amazon.com/images/I/71iH9uY1JKL._AC_SL1500_.jpg",
    "imagen_alt": "VASAGLE escritorio elevable electrico 140x70 grande barato",
    "rating": 4.3,
    "num_reviews": 750,
    "disponible": true,
    "specs": {
      "tipo_motor": "simple",
      "rango_altura_min_cm": 72,
      "rango_altura_max_cm": 120,
      "velocidad_cm_s": 2.5,
      "peso_max_carga_kg": 80,
      "ancho_tablero_cm": 140,
      "profundidad_tablero_cm": 70,
      "peso_estructura_kg": 24,
      "ruido_db": 50,
      "presets_memoria": 4,
      "sistema_anticolision": true,
      "tablero_incluido": true,
      "material_tablero": "melamina",
      "garantia_anos": 3
    },
    "categorias": ["barato", "oficina"],
    "pros": [
      "Tablero de 140x70 por menos de 200 EUR",
      "Anticolision y 4 memorias incluidas",
      "80 kg de carga: mas que otros baratos",
      "Marca conocida con buena logistica"
    ],
    "contras": [
      "Motor simple: velocidad estandar",
      "Garantia de solo 3 anos",
      "Algo pesado (24 kg) para montar solo"
    ],
    "veredicto": "El escritorio grande y barato. 140 cm de tablero por menos de 200 EUR.",
    "puntuacion": {
      "calidad_construccion": 6,
      "estabilidad": 6,
      "facilidad_montaje": 7,
      "relacion_calidad_precio": 9,
      "funcionalidades": 7,
      "total": 7.0
    },
    "ideal_para": "Quien necesita un tablero grande sin pagar precio premium.",
    "slug": "vasagle-lsd302"
  }
}
